{
  "recentFiles": [
    {
      "basename": "note-599",
      "path": "notes/note-599.md"
    },
    {
      "basename": "note-542",
      "path": "notes/note-542.md"
    },
    {
      "basename": "EEAR",
      "path": "MATÉRIAS/EEAR.md"
    },
    {
      "basename": "QUESTÕES ERRADAS DE MATEMÁTICA",
      "path": "notes/MATEMÁTICA/QUESTÕES ERRADAS DE MATEMÁTICA.md"
    },
    {
      "basename": "questões erradas de português",
      "path": "notes/GRAMÁTICA/questões erradas de português.md"
    },
    {
      "basename": "note-476",
      "path": "notes/note-476.md"
    },
    {
      "basename": "note-598",
      "path": "notes/note-598.md"
    },
    {
      "basename": "note-585",
      "path": "notes/note-585.md"
    },
    {
      "basename": "note-546",
      "path": "notes/note-546.md"
    },
    {
      "basename": "ELETRICIDADE",
      "path": "notes/FÍSICA/ELETRICIDADE.md"
    },
    {
      "basename": "DINÂMICA",
      "path": "notes/FÍSICA/DINÂMICA.md"
    },
    {
      "basename": "note-596",
      "path": "notes/note-596.md"
    },
    {
      "basename": "note-143",
      "path": "notes/note-143.md"
    },
    {
      "basename": "tipos de funções",
      "path": "notes/MATEMÁTICA/ÁLGEBRA/Funções/tipos de funções.md"
    },
    {
      "basename": "note-597",
      "path": "notes/note-597.md"
    },
    {
      "basename": "regência verbal",
      "path": "notes/GRAMÁTICA/regência verbal.md"
    },
    {
      "basename": "note-586",
      "path": "notes/note-586.md"
    },
    {
      "basename": "note-595",
      "path": "notes/note-595.md"
    },
    {
      "basename": "note-594",
      "path": "notes/note-594.md"
    },
    {
      "basename": "note-593",
      "path": "notes/note-593.md"
    },
    {
      "basename": "note-592",
      "path": "notes/note-592.md"
    },
    {
      "basename": "note-591",
      "path": "notes/note-591.md"
    },
    {
      "basename": "crase",
      "path": "notes/crase.md"
    },
    {
      "basename": "note-566",
      "path": "notes/note-566.md"
    },
    {
      "basename": "note-590",
      "path": "notes/note-590.md"
    },
    {
      "basename": "note-27",
      "path": "notes/note-27.md"
    },
    {
      "basename": "note-587",
      "path": "notes/note-587.md"
    },
    {
      "basename": "note-589",
      "path": "notes/note-589.md"
    },
    {
      "basename": "note-588",
      "path": "notes/note-588.md"
    },
    {
      "basename": "note-502",
      "path": "notes/note-502.md"
    },
    {
      "basename": "note-543",
      "path": "notes/note-543.md"
    },
    {
      "basename": "note-550",
      "path": "notes/note-550.md"
    },
    {
      "basename": "note-580",
      "path": "notes/note-580.md"
    },
    {
      "basename": "note-488",
      "path": "notes/note-488.md"
    },
    {
      "basename": "note-496",
      "path": "notes/note-496.md"
    },
    {
      "basename": "note-584",
      "path": "notes/note-584.md"
    },
    {
      "basename": "note-583",
      "path": "notes/note-583.md"
    },
    {
      "basename": "note-582",
      "path": "notes/note-582.md"
    },
    {
      "basename": "note-581",
      "path": "notes/note-581.md"
    },
    {
      "basename": "note-554",
      "path": "notes/note-554.md"
    },
    {
      "basename": "note-579",
      "path": "notes/note-579.md"
    },
    {
      "basename": "note-555",
      "path": "notes/note-555.md"
    },
    {
      "basename": "note-556",
      "path": "notes/note-556.md"
    },
    {
      "basename": "note-561",
      "path": "notes/note-561.md"
    },
    {
      "basename": "note-578",
      "path": "notes/note-578.md"
    },
    {
      "basename": "ONDULATÓRIA e ÓTICA",
      "path": "notes/FÍSICA/ONDULATÓRIA e ÓTICA.md"
    },
    {
      "basename": "note-451",
      "path": "notes/note-451.md"
    },
    {
      "basename": "note-577",
      "path": "notes/note-577.md"
    },
    {
      "basename": "note-573",
      "path": "notes/note-573.md"
    },
    {
      "basename": "note-572",
      "path": "notes/note-572.md"
    }
  ],
  "omittedPaths": [],
  "maxLength": null,
  "openType": "tab"
}