{
  "main": {
    "id": "f4ca6a0519e6a5cc",
    "type": "split",
    "children": [
      {
        "id": "6597822893823516",
        "type": "tabs",
        "children": [
          {
            "id": "7467548afbad86c8",
            "type": "leaf",
            "state": {
              "type": "markdown",
              "state": {
                "file": "EAGS SIN/EAGS SIN.md",
                "mode": "source",
                "source": false
              }
            }
          },
          {
            "id": "c51fd8a2af1dcdf9",
            "type": "leaf",
            "state": {
              "type": "markdown",
              "state": {
                "file": "EAGS SIN/TEXTO/uso do ponto e virgula correto.md",
                "mode": "source",
                "source": false
              }
            }
          },
          {
            "id": "4a9f612bd7cca020",
            "type": "leaf",
            "state": {
              "type": "markdown",
              "state": {
                "file": "EAGS SIN/GRAMÁTICA/regras do acento gráfico.md",
                "mode": "source",
                "source": false
              }
            }
          },
          {
            "id": "f8c8b2e11e8eead5",
            "type": "leaf",
            "state": {
              "type": "markdown",
              "state": {
                "file": "EAGS SIN/GRAMÁTICA/gramática normativa.md",
                "mode": "source",
                "source": false
              }
            }
          },
          {
            "id": "b587216282893b9d",
            "type": "leaf",
            "state": {
              "type": "markdown",
              "state": {
                "file": "EAGS SIN/crase.md",
                "mode": "source",
                "source": false
              }
            }
          },
          {
            "id": "fd47859bfd1a8aab",
            "type": "leaf",
            "state": {
              "type": "markdown",
              "state": {
                "file": "EAGS SIN/crase.md",
                "mode": "source",
                "source": false
              }
            }
          }
        ]
      }
    ],
    "direction": "vertical"
  },
  "left": {
    "id": "96841bf50e68c859",
    "type": "split",
    "children": [
      {
        "id": "16aeeeb171d62e0b",
        "type": "tabs",
        "children": [
          {
            "id": "7d2ff1388fc577af",
            "type": "leaf",
            "state": {
              "type": "file-explorer",
              "state": {
                "sortOrder": "alphabetical"
              }
            }
          },
          {
            "id": "46925ea84d43e3d5",
            "type": "leaf",
            "state": {
              "type": "search",
              "state": {
                "query": "",
                "matchingCase": false,
                "explainSearch": false,
                "collapseAll": false,
                "extraContext": false,
                "sortOrder": "alphabetical"
              }
            }
          },
          {
            "id": "20923055f6ed5054",
            "type": "leaf",
            "state": {
              "type": "bookmarks",
              "state": {}
            }
          }
        ]
      }
    ],
    "direction": "horizontal",
    "width": 213.5,
    "collapsed": true
  },
  "right": {
    "id": "ee4e8bcf9413ed0e",
    "type": "split",
    "children": [
      {
        "id": "f0f63b612db2c5c7",
        "type": "tabs",
        "children": [
          {
            "id": "97617361bb2d8f0c",
            "type": "leaf",
            "state": {
              "type": "backlink",
              "state": {
                "file": "EAGS SIN/EAGS SIN.md",
                "collapseAll": false,
                "extraContext": false,
                "sortOrder": "alphabetical",
                "showSearch": false,
                "searchQuery": "",
                "backlinkCollapsed": false,
                "unlinkedCollapsed": true
              }
            }
          },
          {
            "id": "2e9a7c3e1cb9a5a0",
            "type": "leaf",
            "state": {
              "type": "outgoing-link",
              "state": {
                "file": "EAGS SIN/EAGS SIN.md",
                "linksCollapsed": false,
                "unlinkedCollapsed": true
              }
            }
          },
          {
            "id": "327a7dc5c9039840",
            "type": "leaf",
            "state": {
              "type": "tag",
              "state": {
                "sortOrder": "frequency",
                "useHierarchy": true
              }
            }
          },
          {
            "id": "7ac33a9623b6150c",
            "type": "leaf",
            "state": {
              "type": "outline",
              "state": {
                "file": "EAGS SIN/EAGS SIN.md"
              }
            }
          },
          {
            "id": "11b1fa667acb16ac",
            "type": "leaf",
            "state": {
              "type": "all-properties",
              "state": {
                "sortOrder": "frequency"
              }
            }
          }
        ],
        "currentTab": 3
      }
    ],
    "direction": "horizontal",
    "width": 200,
    "collapsed": true
  },
  "left-ribbon": {
    "hiddenItems": {
      "switcher:Open quick switcher": false,
      "graph:Open graph view": false,
      "canvas:Create new canvas": false,
      "daily-notes:Open today's daily note": false,
      "templates:Insert template": false,
      "command-palette:Open command palette": false,
      "obsidian-importer:Open Importer": false
    }
  },
  "active": "7467548afbad86c8",
  "lastOpenFiles": [
    "EAGS SIN/TEXTO/uso do ponto e virgula correto.md",
    "EAGS SIN/EAGS SIN.md",
    "EAGS SIN/GRAMÁTICA/regras do acento gráfico.md",
    "EAGS SIN/GRAMÁTICA/gramática normativa.md",
    "EAGS SIN/crase.md",
    "Task-To-Do/Task To Do.md",
    "EAGS SIN/GRAMÁTICA/concordância nominal.md",
    "EAGS SIN/GRAMÁTICA/colocação pronominal.md",
    "EAGS SIN/GRAMÁTICA/quando usar o x ou ch.md",
    "EAGS SIN/GRAMÁTICA/quando usar o ch.md",
    "EAGS SIN/TEXTO/uso da virgula correto.md",
    "subordinadas adverbias cada tipo explicado.md",
    "EAGS SIN/GRAMÁTICA/concordância verbal.md",
    "EAGS SIN/GRAMÁTICA/processo de derivação/parassintética.md",
    "EAGS SIN/GRAMÁTICA/Usos da Partícula Se.pdf",
    "uso da particula se.md",
    "EAGS SIN/GRAMÁTICA/pronome pessoais (neles se incluem os pronomes de tratamento).md",
    "EAGS SIN/GRAMÁTICA/processo de derivação",
    "EAGS SIN/GRAMÁTICA/diferença entre pronomes substantivos e pronomes adjetivos.md",
    "EAGS SIN/GRAMÁTICA/pronome/7 erros com pronomes pessoais.md",
    "EAGS SIN/GRAMÁTICA/pronomes demonstrativos a(s) o(s).md",
    "pronomes demonstrativos.md",
    "EAGS SIN/GRAMÁTICA/pronome interrogativos.md",
    "EAGS SIN/GRAMÁTICA/pronomes relativos.md",
    "EAGS SIN/diferença entre pronome relativo e pronome interrogativo.md",
    "EAGS SIN/GRAMÁTICA/Unconfirmed 438243.crdownload",
    "EAGS SIN/GRAMÁTICA/eags-2007-sin-11).md",
    "Untitled.canvas",
    "EAGS SIN/GRAMÁTICA/flexão de grau de advérbio.md",
    "EAGS SIN/GRAMÁTICA/valores caracteristico de pronomes.md",
    "imagens/Pasted image 20230926180753.png",
    "EAGS SIN/GRAMÁTICA/oração",
    "EAGS SIN/GRAMÁTICA/ORTOGRAFIA",
    "imagens/Pasted image 20230917212314.png",
    "imagens/Pasted image 20230915212011.png",
    "EAGS SIN/GRAMÁTICA/pronome",
    "EAGS SIN/GRAMÁTICA/Morfologia/Sinxtaxe",
    "EAGS SIN/GRAMÁTICA/Morfologia",
    "EAGS SIN/GRAMÁTICA",
    "EAGS SIN/TEXTO/Untitled",
    "imagens/classes_de_rede.jpg",
    "imagens/Pasted image 20230912145836.png",
    "imagens/Pasted image 20230911151316.png",
    "HTML import/Attachments/youtube-bg.png",
    "HTML import/Attachments/7graus-logo.svg",
    "sites/Homônimos e Parônimos - Toda Matéria_files/7graus-logo.svg",
    "sites/Homônimos e Parônimos - Toda Matéria_files/desktop-logo.png",
    "Untitled 1.canvas"
  ]
}